pythonipc/__init__.py
pythonipc/pyIpc.py
pythonipc-1.4.2.dist-info/LICENSE
pythonipc-1.4.2.dist-info/METADATA
pythonipc-1.4.2.dist-info/WHEEL
pythonipc-1.4.2.dist-info/top_level.txt
pythonipc-1.4.2.dist-info/RECORD
